websumm_agent/__init__.py
websumm_agent/main.py
websumm_agent/prompts.py
websumm_agent-2025.12.21193658.dist-info/METADATA
websumm_agent-2025.12.21193658.dist-info/WHEEL
websumm_agent-2025.12.21193658.dist-info/top_level.txt
websumm_agent-2025.12.21193658.dist-info/RECORD
