Metadata-Version: 2.4
Name: websumm-agent
Version: 2025.12.21193658
Summary: Efficient web information retrieval and summation without excessive token usage.
Author-email: websumm-agent <hi@eugene.plus>
License: MIT
Project-URL: Homepage, https://github.com/chigwell/websumm-agent
Requires-Python: >=3.9
Requires-Dist: langchain-llm7>=0.0.0
Requires-Dist: llmatch-messages>=0.0.0
Requires-Dist: langchain-core>=0.3.0
